src/CLIColors/__init__.py
src/CLIColors/clicolorizer.py
clicolorizer-0.0.1.dist-info/METADATA
clicolorizer-0.0.1.dist-info/WHEEL
clicolorizer-0.0.1.dist-info/licenses/LICENSE
clicolorizer-0.0.1.dist-info/RECORD
