Metadata-Version: 2.1
Name: CLIColorizer
Version: 0.0.1
Summary: A simple way to color and style CLI text in Python.
Project-URL: Homepage, https://github.com/davebowlin/Colorizer
Author-email: Dave Bowlin <davebowlin@gmail.com>
License-Expression: MIT
License-File: LICENSE
Classifier: License :: OSI Approved :: MIT License
Classifier: Operating System :: OS Independent
Classifier: Programming Language :: Python :: 3
Requires-Python: >=3.7
